MANIFEST.in
README.txt
setup.cfg
setup.py
docs/HISTORY.txt
docs/INSTALL.txt
docs/LICENSE.GPL
docs/LICENSE.txt
redomino/__init__.py
redomino.qwerty_theme.egg-info/PKG-INFO
redomino.qwerty_theme.egg-info/SOURCES.txt
redomino.qwerty_theme.egg-info/dependency_links.txt
redomino.qwerty_theme.egg-info/entry_points.txt
redomino.qwerty_theme.egg-info/namespace_packages.txt
redomino.qwerty_theme.egg-info/not-zip-safe
redomino.qwerty_theme.egg-info/requires.txt
redomino.qwerty_theme.egg-info/top_level.txt
redomino/qwerty_theme/__init__.py
redomino/qwerty_theme/configure.zcml
redomino/qwerty_theme/profiles.zcml
redomino/qwerty_theme/skins.zcml
redomino/qwerty_theme/version.txt
redomino/qwerty_theme/browser/__init__.py
redomino/qwerty_theme/browser/configure.zcml
redomino/qwerty_theme/browser/interfaces.py
redomino/qwerty_theme/browser/images/background-box.png
redomino/qwerty_theme/browser/images/dot.png
redomino/qwerty_theme/browser/images/footer.png
redomino/qwerty_theme/browser/images/gradient-menu-3livello.jpg
redomino/qwerty_theme/browser/images/gradient-slide.png
redomino/qwerty_theme/browser/images/header-bg.png
redomino/qwerty_theme/browser/images/separatore.png
redomino/qwerty_theme/browser/stylesheets/ploneIE7Custom.css
redomino/qwerty_theme/browser/stylesheets/ploneIE8Custom.css
redomino/qwerty_theme/browser/stylesheets/qwerty_theme.css
redomino/qwerty_theme/profiles/default/cssregistry.xml
redomino/qwerty_theme/profiles/default/metadata.xml
redomino/qwerty_theme/profiles/default/redomino.qwerty_theme_various.txt
redomino/qwerty_theme/profiles/default/skins.xml
redomino/qwerty_theme/skins/redomino_qwerty_theme/header-bg.png
redomino/qwerty_theme/skins/redomino_qwerty_theme/main_template.pt
redomino/qwerty_theme/skins/redomino_qwerty_theme/texture-header.png