Metadata-Version: 1.0
Name: redomino.qwerty_theme
Version: 1.3
Summary: An installable theme for based on redomino.css3theme
Home-page: https://github.com/redomino/redomino.qwerty_theme
Author: Andrea D'Este
Author-email: andrea.deste@redomino.com
License: GPL
Keywords: plone theme autoadaptative
Platform: UNKNOWN
Classifier: Framework :: Plone
Classifier: Programming Language :: Python
